LICENSE
MANIFEST.in
README.rst
setup.py
jobmonitor/FlaskWithJobResolvers.py
jobmonitor/__init__.py
jobmonitor/catchall.py
jobmonitor/config.py
jobmonitor/jobs.py
jobmonitor/start_worker.py
jobmonitor.egg-info/PKG-INFO
jobmonitor.egg-info/SOURCES.txt
jobmonitor.egg-info/dependency_links.txt
jobmonitor.egg-info/requires.txt
jobmonitor.egg-info/top_level.txt
jobmonitor/static/favicon.ico
jobmonitor/static/javascripts/jobmonitor.js
jobmonitor/static/javascripts/lib/bootstrap.min.js
jobmonitor/static/javascripts/lib/d3.chart.histograms.min.js
jobmonitor/static/javascripts/lib/d3.chart.min.js
jobmonitor/static/javascripts/lib/d3.min.js
jobmonitor/static/javascripts/lib/jquery.min.js
jobmonitor/static/javascripts/lib/spin.min.js
jobmonitor/static/stylesheets/bootstrap-datepicker.css
jobmonitor/static/stylesheets/jobmonitor.css
jobmonitor/static/stylesheets/lib/bootstrap.min.css
jobmonitor/templates/_helpers.html
jobmonitor/templates/layout.html
jobmonitor/templates/two_column_sidebar.html
jobmonitor/templates/errors/404.html