Metadata-Version: 1.1
Name: jobmonitor
Version: 0.0.4
Summary: Physics-orientated job monitoring over HTTP with Flask.
Home-page: https://github.com/alexpearce/jobmonitor
Author: Alex Pearce
Author-email: alex@alexpearce.me
License: The MIT License (MIT)
